nbmessages/__init__.py
nbmessages/base.py
nbmessages/etc.py
nbmessages/markdown.py
nbmessages/message.py
nbmessages/notification.py
nbmessages/users.py
nbmessages/utils.py
nbmessages/extensions/__init__.py
nbmessages/extensions/admin/__init__.py
nbmessages/extensions/message/__init__.py
nbmessages/extensions/message/__pycache__/__init__.cpython-37.pyc
nbmessages/extensions/message/__pycache__/__init__.cpython-38.pyc
nbmessages/nbextensions/__init__.py
nbmessages/nbextensions/admin/bootstrap-datepicker.js
nbmessages/nbextensions/admin/main.js
nbmessages/nbextensions/message/main.js
nbmessages-0.0.24.data/data/nbmessages/nbmessages-config.yaml
nbmessages-0.0.24.data/data/nbmessages/css/bootstrap-datepicker.min.css
nbmessages-0.0.24.data/data/nbmessages/css/nbmessages.css
nbmessages-0.0.24.data/data/nbmessages/images/envelope.svg
nbmessages-0.0.24.data/data/nbmessages/images/ucsd-0.png
tests/__init__.py
tests/acceptance/__init__.py
tests/acceptance/test_general.py
tests/acceptance/test_message_creation.py
tests/acceptance/test_message_delete.py
tests/acceptance/test_security.py
tests/mocks/nbmessages-config.yaml
tests/mocks/something.txt
tests/mocks/test-markdown.md
tests/mocks/users.txt
tests/mocks/messages/20200503.md
tests/mocks/messages/20200505.md
tests/unit/__init__.py
tests/unit/test_base.py
tests/unit/test_markdown.py
tests/unit/test_message.py
tests/unit/test_notification.py
tests/unit/test_users.py
tests/unit/test_utils.py
nbmessages-0.0.24.dist-info/LICENSE
nbmessages-0.0.24.dist-info/METADATA
nbmessages-0.0.24.dist-info/WHEEL
nbmessages-0.0.24.dist-info/top_level.txt
nbmessages-0.0.24.dist-info/RECORD
