Metadata-Version: 2.1
Name: nbmessages
Version: 0.0.24
Summary: Post messages in a jupyter notebook to other users
Home-page: https://github.com/ucsd-ets/nbmessages
Author: Wesley Uykimpang
Author-email: UNKNOWN
License: UNKNOWN
Platform: UNKNOWN
Classifier: Operating System :: POSIX :: Linux
Classifier: Intended Audience :: Developers
Classifier: Intended Audience :: Education
Requires-Dist: pyyaml
Requires-Dist: beautifulsoup4
Requires-Dist: oo-tools (==0.2.0)
Requires-Dist: markdown
